{
    "food": [
        {
            "id": 1,
            "title": "دلمه برگ کلم",
            "favorite": false,
            "lastPrice": "220,000",
            "price": "۲۰۹٬۰۰۰",
            "stare": "5",
            "discount": "%12",
            "point": "52 امتیاز",
            "img": "/src/assets/Images/img/img1.png"
        },
        {
            "id": 2,
            "title": "بادمجان شکم‌پر",
            "favorite": false,
            "lastPrice": "۱۳۶٬۰۰۰",
            "price": "۱۳۶٬۰۰۰",
            "stare": "4",
            "discount": "%18",
            "point": "31 امتیاز",
            "img": "/src/assets/Images/img/img2.png"
        },
        {
            "id": 3,
            "title": "کالزونه اسفناج",
            "favorite": false,
            "lastPrice": "۱۷۷٬۰۰۰",
            "price": "۱۷۷٬۰۰۰",
            "stare": "5",
            "discount": "%17",
            "point": "56 امتیاز",
            "img": "/src/assets/Images/img/img3.png"
        },
        {
            "id": 4,
            "title": "پیتزا قارچ",
            "favorite": false,
            "lastPrice": "215,000",
            "price": "۱۷۵٬۰۰۰",
            "stare": "3",
            "discount": "%25",
            "point": "17 امتیاز",
            "img": "/src/assets/Images/img/img4.png"
        },
        {
            "id": 5,
            "title": "پنینی اسفناج",
            "favorite": false,
            "price": "۱۹۰٬۰۰۰",
            "stare": "5",
            "discount": "%15",
            "point": "18 امتیاز",
            "img": "/src/assets/Images/img/image5.png"
        },
        {
            "id": 6,
            "title": "پیتزا پپرونی",
            "favorite": false,
            "price": "۱۰۰٬۰۰۰",
            "stare": "5",
            "discount": "%45",
            "point": "36 امتیاز",
            "img": "/src/assets/Images/img/image6.png"
        },
        {
            "id": 7,
            "title": "راتاتویی",
            "favorite": false,
            "price": "۹۵٬۰۰۰",
            "stare": "3",
            "discount": "%18",
            "point": "47 امتیاز",
            "img": "/src/assets/Images/img/image7.png"
        },
        {
            "id": 8,
            "title": "بورانی بادمجان",
            "favorite": false,
            "price": "۱۴۸٬۰۰۰",
            "stare": "4",
            "discount": "%22",
            "point": "42 امتیاز",
            "img": "/src/assets/Images/img/image8.png"
        },
        {
            "id": 9,
            "title": "سوشی",
            "favorite": false,
            "price": "۸۵٬۰۰۰",
            "stare": "5",
            "discount": "%15",
            "point": "15 امتیاز",
            "img": "/src/assets/Images/img/image9.png"
        },
        {
            "id": 10,
            "title": "راتاتویی",
            "favorite": false,
            "price": "۹۵٬۰۰۰",
            "stare": "3",
            "discount": "%45",
            "point": "32 امتیاز",
            "img": "/src/assets/Images/img/image10.png"
        },
        {
            "id": 11,
            "title": "پاکورا سبزیجات",
            "favorite": false,
            "price": "۱۱۰٬۰۰۰",
            "stare": "5",
            "discount": "%8",
            "point": "50 امتیاز",
            "img": "/src/assets/Images/img/image11.png"
        },
        {
            "id": 12,
            "title": "لازانیا",
            "favorite": false,
            "price": "۱۵۰٬۰۰۰",
            "stare": "4",
            "discount": "%18",
            "point": "54 امتیاز",
            "img": "/src/assets/Images/img/image12.png"
        },
        {
            "id": 13,
            "title": "پاستا سبزیجات",
            "favorite": false,
            "price": "۹۵٬۰۰۰",
            "stare": "5",
            "discount": "%11",
            "point": "40 امتیاز",
            "img": "/src/assets/Images/img/image13.png"
        }
    ]
}